README.md
setup.py
cloudyskysoftware_pulumi_render/__init__.py
cloudyskysoftware_pulumi_render/_utilities.py
cloudyskysoftware_pulumi_render/provider.py
cloudyskysoftware_pulumi_render/pulumi-plugin.json
cloudyskysoftware_pulumi_render/py.typed
cloudyskysoftware_pulumi_render.egg-info/PKG-INFO
cloudyskysoftware_pulumi_render.egg-info/SOURCES.txt
cloudyskysoftware_pulumi_render.egg-info/dependency_links.txt
cloudyskysoftware_pulumi_render.egg-info/not-zip-safe
cloudyskysoftware_pulumi_render.egg-info/requires.txt
cloudyskysoftware_pulumi_render.egg-info/top_level.txt
cloudyskysoftware_pulumi_render/config/__init__.py
cloudyskysoftware_pulumi_render/config/vars.py
cloudyskysoftware_pulumi_render/services/__init__.py
cloudyskysoftware_pulumi_render/services/_enums.py
cloudyskysoftware_pulumi_render/services/_inputs.py
cloudyskysoftware_pulumi_render/services/custom_domain.py
cloudyskysoftware_pulumi_render/services/deploy.py
cloudyskysoftware_pulumi_render/services/outputs.py
cloudyskysoftware_pulumi_render/services/scale.py
cloudyskysoftware_pulumi_render/services/service.py
cloudyskysoftware_pulumi_render/services/suspend.py