Metadata-Version: 2.1
Name: cloudyskysoftware-pulumi-render
Version: 0.0.26
Summary: A Pulumi package for creating and managing Render resources.
Home-page: https://cloudysky.software
License: Apache-2.0
Project-URL: Repository, https://github.com/cloudy-sky-software/pulumi-render
Keywords: pulumi render category/cloud kind/native
Platform: UNKNOWN
